pyvitemadose/__init__.py
pyvitemadose/args.py
pyvitemadose/pyvitemadose.py
pyvitemadose/update.py
pyvitemadose-1.1.0.dist-info/LICENSE.txt
pyvitemadose-1.1.0.dist-info/METADATA
pyvitemadose-1.1.0.dist-info/WHEEL
pyvitemadose-1.1.0.dist-info/entry_points.txt
pyvitemadose-1.1.0.dist-info/top_level.txt
pyvitemadose-1.1.0.dist-info/RECORD
